sphinx_unpack/.DS_Store
sphinx_unpack/__init__.py
sphinx_unpack/py.typed
sphinx_unpack/version.py
sphinx_unpack-0.0.2.dist-info/licenses/LICENSE
sphinx_unpack-0.0.2.dist-info/WHEEL
sphinx_unpack-0.0.2.dist-info/METADATA
sphinx_unpack-0.0.2.dist-info/RECORD
